comuni_italiani/__init__.py
comuni_italiani/admin.py
comuni_italiani/apps.py
comuni_italiani/models.py
comuni_italiani/tests.py
comuni_italiani/urls.py
comuni_italiani/views.py
comuni_italiani/autocomplete/__init__.py
comuni_italiani/autocomplete/apps.py
comuni_italiani/autocomplete/urls.py
comuni_italiani/autocomplete/views.py
comuni_italiani/fixtures/comuni_italiani.json
comuni_italiani/fixtures/elenco-comuni-italiani.csv
comuni_italiani/fixtures/ripartizioni-reg-prov-cm.csv
comuni_italiani/management/__init__.py
comuni_italiani/management/commands/__init__.py
comuni_italiani/management/commands/import_comuni.py
comuni_italiani/management/commands/import_regioni_prov.py
comuni_italiani/migrations/0001_initial.py
comuni_italiani/migrations/__init__.py
django_comuni_italiani-1.4.1.dist-info/LICENSE
django_comuni_italiani-1.4.1.dist-info/METADATA
django_comuni_italiani-1.4.1.dist-info/WHEEL
django_comuni_italiani-1.4.1.dist-info/top_level.txt
django_comuni_italiani-1.4.1.dist-info/RECORD
