Metadata-Version: 2.1
Name: django-comuni-italiani
Version: 1.4.1
Summary: A simple django (>= 1.7) app for Italian cities and regions
Home-page: https://github.com/kbytesys/django_comuni_italiani
Author: Andrea Briganti
Author-email: kbytesys@gmail.com
License: GNU LGPL v2
Download-URL: https://github.com/kbytesys/django_comuni_italiani/tarball/v1.3.0
Keywords: django,comuni,regioni,province
Platform: UNKNOWN
Classifier: Development Status :: 5 - Production/Stable
Classifier: Environment :: Web Environment
Classifier: Intended Audience :: Developers
Classifier: License :: OSI Approved :: GNU Lesser General Public License v2 (LGPLv2)
Classifier: Natural Language :: Italian
Classifier: Programming Language :: Python
Classifier: Programming Language :: Python :: 3
Classifier: Framework :: Django
Classifier: Framework :: Django :: 1.7
Classifier: Framework :: Django :: 1.8
Classifier: Framework :: Django :: 1.9
Classifier: Framework :: Django :: 1.10
Classifier: Framework :: Django :: 1.11
Classifier: Framework :: Django :: 2.0
Classifier: Framework :: Django :: 2.1
Classifier: Operating System :: OS Independent
Classifier: Topic :: Internet :: WWW/HTTP
Classifier: Topic :: Software Development :: Libraries :: Python Modules
Requires-Dist: Django (>=1.7)
